LICENSE
MANIFEST.in
README.rst
setup.cfg
setup.py
versioneer.py
tests/__init__.py
tests/test_general.py
tpRigToolkit/__init__.py
tpRigToolkit/tools/__init__.py
tpRigToolkit/tools/symmesh/__init__.py
tpRigToolkit/tools/symmesh/__logging__.ini
tpRigToolkit/tools/symmesh/__version__.py
tpRigToolkit/tools/symmesh/_version.py
tpRigToolkit/tools/symmesh/core/__init__.py
tpRigToolkit/tools/symmesh/core/client.py
tpRigToolkit/tools/symmesh/core/consts.py
tpRigToolkit/tools/symmesh/core/controller.py
tpRigToolkit/tools/symmesh/core/model.py
tpRigToolkit/tools/symmesh/core/symmesh.py
tpRigToolkit/tools/symmesh/core/tool.py
tpRigToolkit/tools/symmesh/core/toolset.py
tpRigToolkit/tools/symmesh/core/view.py
tpRigToolkit/tools/symmesh/dccs/__init__.py
tpRigToolkit/tools/symmesh/dccs/maya/__init__.py
tpRigToolkit/tools/symmesh/dccs/maya/server.py
tpRigToolkit/tools/symmesh/widgets/__init__.py
tpRigToolkit/tools/symmesh/widgets/symmesh.py
tpRigToolkit_tools_symmesh.egg-info/PKG-INFO
tpRigToolkit_tools_symmesh.egg-info/SOURCES.txt
tpRigToolkit_tools_symmesh.egg-info/dependency_links.txt
tpRigToolkit_tools_symmesh.egg-info/not-zip-safe
tpRigToolkit_tools_symmesh.egg-info/requires.txt
tpRigToolkit_tools_symmesh.egg-info/top_level.txt