Metadata-Version: 2.1
Name: tpRigToolkit-tools-symmesh
Version: 0.0.1
Summary: Tool to build symmetrical and meshes. Based on the amazing abSymMesh MEL script.
Home-page: https://github.com/tpRigToolkit/tpRigToolkit-tools-symmesh
Author: Tomas Poveda
Author-email: tpovedatd@gmail.com
License: MIT
Platform: UNKNOWN
Provides-Extra: dev
Provides-Extra: test
